{
  "2025-09-15": {
    "breadcrumbs": {
      "invalid": "N/A",
      "valid": "N/A"
    },
    "coverage": {
      "not_indexed": "N/A",
      "indexed": "N/A",
      "impressions": 46
    },
    "https": {
      "non_https_urls": 0,
      "https_urls": 25
    },
    "video_indexing": {
      "no_video_indexed": 11,
      "video_indexed": 0,
      "impressions": 0
    }
  },
  "2025-09-16": {
    "breadcrumbs": {
      "invalid": "N/A",
      "valid": "N/A"
    },
    "coverage": {
      "not_indexed": 4,
      "indexed": 45,
      "impressions": 35
    },
    "https": {
      "non_https_urls": 0,
      "https_urls": 25
    },
    "video_indexing": {
      "no_video_indexed": 11,
      "video_indexed": 0,
      "impressions": 0
    }
  },
  "2025-09-17": {
    "breadcrumbs": {
      "invalid": "N/A",
      "valid": "N/A"
    },
    "coverage": {
      "not_indexed": 4,
      "indexed": 55,
      "impressions": 23
    },
    "https": {
      "non_https_urls": 0,
      "https_urls": 25
    },
    "video_indexing": {
      "no_video_indexed": 11,
      "video_indexed": 0,
      "impressions": 0
    }
  },
  "2025-09-18": {
    "breadcrumbs": {
      "invalid": "N/A",
      "valid": "N/A"
    },
    "coverage": {
      "not_indexed": 4,
      "indexed": 55,
      "impressions": 33
    },
    "https": {
      "non_https_urls": 0,
      "https_urls": 25
    },
    "video_indexing": {
      "no_video_indexed": 11,
      "video_indexed": 0,
      "impressions": 0
    }
  },
  "2025-09-19": {
    "breadcrumbs": {
      "invalid": "N/A",
      "valid": "N/A"
    },
    "coverage": {
      "not_indexed": 4,
      "indexed": 55,
      "impressions": 41
    },
    "https": {
      "non_https_urls": 0,
      "https_urls": 24
    },
    "video_indexing": {
      "no_video_indexed": 16,
      "video_indexed": 0,
      "impressions": 0
    }
  },
  "2025-09-20": {
    "breadcrumbs": {
      "invalid": "N/A",
      "valid": "N/A"
    },
    "coverage": {
      "not_indexed": 4,
      "indexed": 55,
      "impressions": 46
    },
    "https": {
      "non_https_urls": 0,
      "https_urls": 34
    },
    "video_indexing": {
      "no_video_indexed": 16,
      "video_indexed": 0,
      "impressions": 0
    }
  },
  "2025-09-21": {
    "breadcrumbs": {
      "invalid": "N/A",
      "valid": "N/A"
    },
    "coverage": {
      "not_indexed": 9,
      "indexed": 60,
      "impressions": 44
    },
    "https": {
      "non_https_urls": 0,
      "https_urls": 34
    },
    "video_indexing": {
      "no_video_indexed": 16,
      "video_indexed": 0,
      "impressions": 0
    }
  },
  "2025-09-22": {
    "breadcrumbs": {
      "invalid": "N/A",
      "valid": "N/A"
    },
    "coverage": {
      "not_indexed": 9,
      "indexed": 60,
      "impressions": 33
    },
    "https": {
      "non_https_urls": 0,
      "https_urls": 34
    },
    "video_indexing": {
      "no_video_indexed": 16,
      "video_indexed": 0,
      "impressions": 0
    }
  },
  "2025-09-23": {
    "breadcrumbs": {
      "invalid": "N/A",
      "valid": "N/A"
    },
    "coverage": {
      "not_indexed": 9,
      "indexed": 60,
      "impressions": 35
    },
    "https": {
      "non_https_urls": 0,
      "https_urls": 33
    },
    "video_indexing": {
      "no_video_indexed": 17,
      "video_indexed": 0,
      "impressions": 0
    }
  },
  "2025-09-24": {
    "breadcrumbs": {
      "invalid": "N/A",
      "valid": "N/A"
    },
    "coverage": {
      "not_indexed": 4,
      "indexed": 76,
      "impressions": 38
    },
    "https": {
      "non_https_urls": 0,
      "https_urls": 44
    },
    "video_indexing": {
      "no_video_indexed": 17,
      "video_indexed": 0,
      "impressions": 0
    }
  },
  "2025-09-25": {
    "breadcrumbs": {
      "invalid": "N/A",
      "valid": "N/A"
    },
    "coverage": {
      "not_indexed": 4,
      "indexed": 76,
      "impressions": 42
    },
    "https": {
      "non_https_urls": 0,
      "https_urls": 38
    },
    "video_indexing": {
      "no_video_indexed": 17,
      "video_indexed": 0,
      "impressions": 0
    }
  },
  "2025-09-26": {
    "breadcrumbs": {
      "invalid": "N/A",
      "valid": "N/A"
    },
    "coverage": {
      "not_indexed": 4,
      "indexed": 76,
      "impressions": 40
    },
    "https": {
      "non_https_urls": 0,
      "https_urls": 44
    },
    "video_indexing": {
      "no_video_indexed": 18,
      "video_indexed": 0,
      "impressions": 0
    }
  },
  "2025-09-27": {
    "breadcrumbs": {
      "invalid": "N/A",
      "valid": "N/A"
    },
    "coverage": {
      "not_indexed": 4,
      "indexed": 76,
      "impressions": 43
    },
    "https": {
      "non_https_urls": 0,
      "https_urls": 39
    },
    "video_indexing": {
      "no_video_indexed": 18,
      "video_indexed": 0,
      "impressions": 0
    }
  },
  "2025-09-28": {
    "breadcrumbs": {
      "invalid": "N/A",
      "valid": "N/A"
    },
    "coverage": {
      "not_indexed": 14,
      "indexed": 88,
      "impressions": 50
    },
    "https": {
      "non_https_urls": 0,
      "https_urls": 34
    },
    "video_indexing": {
      "no_video_indexed": 18,
      "video_indexed": 0,
      "impressions": 0
    }
  },
  "2025-09-29": {
    "breadcrumbs": {
      "invalid": "N/A",
      "valid": "N/A"
    },
    "coverage": {
      "not_indexed": 14,
      "indexed": 88,
      "impressions": 41
    },
    "https": {
      "non_https_urls": 0,
      "https_urls": 46
    },
    "video_indexing": {
      "no_video_indexed": 18,
      "video_indexed": 0,
      "impressions": 0
    }
  },
  "2025-09-30": {
    "breadcrumbs": {
      "invalid": "N/A",
      "valid": "N/A"
    },
    "coverage": {
      "not_indexed": 14,
      "indexed": 88,
      "impressions": 30
    },
    "https": {
      "non_https_urls": 0,
      "https_urls": 46
    },
    "video_indexing": {
      "no_video_indexed": 19,
      "video_indexed": 0,
      "impressions": 0
    }
  },
  "2025-10-01": {
    "breadcrumbs": {
      "invalid": "N/A",
      "valid": "N/A"
    },
    "coverage": {
      "not_indexed": 8,
      "indexed": 119,
      "impressions": 52
    },
    "https": {
      "non_https_urls": 0,
      "https_urls": 56
    },
    "video_indexing": {
      "no_video_indexed": 19,
      "video_indexed": 0,
      "impressions": 0
    }
  },
  "2025-10-02": {
    "breadcrumbs": {
      "invalid": "N/A",
      "valid": "N/A"
    },
    "coverage": {
      "not_indexed": 8,
      "indexed": 119,
      "impressions": 61
    },
    "https": {
      "non_https_urls": 0,
      "https_urls": 67
    },
    "video_indexing": {
      "no_video_indexed": 19,
      "video_indexed": 0,
      "impressions": 0
    }
  },
  "2025-10-03": {
    "breadcrumbs": {
      "invalid": "N/A",
      "valid": "N/A"
    },
    "coverage": {
      "not_indexed": 8,
      "indexed": 119,
      "impressions": 87
    },
    "https": {
      "non_https_urls": 0,
      "https_urls": 67
    },
    "video_indexing": {
      "no_video_indexed": 19,
      "video_indexed": 0,
      "impressions": 0
    }
  },
  "2025-10-04": {
    "breadcrumbs": {
      "invalid": "N/A",
      "valid": "N/A"
    },
    "coverage": {
      "not_indexed": 8,
      "indexed": 119,
      "impressions": 104
    },
    "https": {
      "non_https_urls": 0,
      "https_urls": 74
    },
    "video_indexing": {
      "no_video_indexed": 19,
      "video_indexed": 0,
      "impressions": 0
    }
  },
  "2025-10-05": {
    "breadcrumbs": {
      "invalid": "N/A",
      "valid": "N/A"
    },
    "coverage": {
      "not_indexed": 147,
      "indexed": 130,
      "impressions": 77
    },
    "https": {
      "non_https_urls": 0,
      "https_urls": 83
    },
    "video_indexing": {
      "no_video_indexed": 19,
      "video_indexed": 0,
      "impressions": 0
    }
  },
  "2025-10-06": {
    "breadcrumbs": {
      "invalid": "N/A",
      "valid": "N/A"
    },
    "coverage": {
      "not_indexed": 147,
      "indexed": 130,
      "impressions": 67
    },
    "https": {
      "non_https_urls": 0,
      "https_urls": 78
    },
    "video_indexing": {
      "no_video_indexed": 19,
      "video_indexed": 0,
      "impressions": 0
    }
  },
  "2025-10-07": {
    "breadcrumbs": {
      "invalid": "N/A",
      "valid": "N/A"
    },
    "coverage": {
      "not_indexed": 147,
      "indexed": 130,
      "impressions": 83
    },
    "https": {
      "non_https_urls": 0,
      "https_urls": 78
    },
    "video_indexing": {
      "no_video_indexed": 19,
      "video_indexed": 0,
      "impressions": 0
    }
  },
  "2025-10-08": {
    "breadcrumbs": {
      "invalid": "N/A",
      "valid": "N/A"
    },
    "coverage": {
      "not_indexed": 4,
      "indexed": 130,
      "impressions": 67
    },
    "https": {
      "non_https_urls": 0,
      "https_urls": 73
    },
    "video_indexing": {
      "no_video_indexed": 19,
      "video_indexed": 0,
      "impressions": 0
    }
  },
  "2025-10-09": {
    "breadcrumbs": {
      "invalid": "N/A",
      "valid": "N/A"
    },
    "coverage": {
      "not_indexed": 4,
      "indexed": 130,
      "impressions": 85
    },
    "https": {
      "non_https_urls": 0,
      "https_urls": 70
    },
    "video_indexing": {
      "no_video_indexed": 19,
      "video_indexed": 0,
      "impressions": 0
    }
  },
  "2025-10-10": {
    "breadcrumbs": {
      "invalid": "N/A",
      "valid": "N/A"
    },
    "coverage": {
      "not_indexed": 4,
      "indexed": 130,
      "impressions": 48
    },
    "https": {
      "non_https_urls": 0,
      "https_urls": 65
    },
    "video_indexing": {
      "no_video_indexed": 19,
      "video_indexed": 0,
      "impressions": 0
    }
  },
  "2025-10-11": {
    "breadcrumbs": {
      "invalid": "N/A",
      "valid": "N/A"
    },
    "coverage": {
      "not_indexed": 4,
      "indexed": 130,
      "impressions": 52
    },
    "https": {
      "non_https_urls": 0,
      "https_urls": 60
    },
    "video_indexing": {
      "no_video_indexed": 19,
      "video_indexed": 0,
      "impressions": 0
    }
  },
  "2025-10-12": {
    "breadcrumbs": {
      "invalid": "N/A",
      "valid": "N/A"
    },
    "coverage": {
      "not_indexed": 7,
      "indexed": 128,
      "impressions": 61
    },
    "https": {
      "non_https_urls": 0,
      "https_urls": 57
    },
    "video_indexing": {
      "no_video_indexed": 19,
      "video_indexed": 0,
      "impressions": 0
    }
  },
  "2025-10-13": {
    "breadcrumbs": {
      "invalid": "N/A",
      "valid": "N/A"
    },
    "coverage": {
      "not_indexed": 7,
      "indexed": 128,
      "impressions": 54
    },
    "https": {
      "non_https_urls": 0,
      "https_urls": 50
    },
    "video_indexing": {
      "no_video_indexed": 19,
      "video_indexed": 0,
      "impressions": 0
    }
  },
  "2025-10-14": {
    "breadcrumbs": {
      "invalid": "N/A",
      "valid": "N/A"
    },
    "coverage": {
      "not_indexed": 7,
      "indexed": 128,
      "impressions": 45
    },
    "https": {
      "non_https_urls": 0,
      "https_urls": 47
    },
    "video_indexing": {
      "no_video_indexed": 19,
      "video_indexed": 0,
      "impressions": 0
    }
  },
  "2025-10-15": {
    "breadcrumbs": {
      "invalid": "N/A",
      "valid": "N/A"
    },
    "coverage": {
      "not_indexed": 8,
      "indexed": 127,
      "impressions": 46
    },
    "https": {
      "non_https_urls": 0,
      "https_urls": 39
    },
    "video_indexing": {
      "no_video_indexed": 19,
      "video_indexed": 0,
      "impressions": 0
    }
  },
  "2025-10-16": {
    "breadcrumbs": {
      "invalid": "N/A",
      "valid": "N/A"
    },
    "coverage": {
      "not_indexed": 8,
      "indexed": 127,
      "impressions": 74
    },
    "https": {
      "non_https_urls": 0,
      "https_urls": 36
    },
    "video_indexing": {
      "no_video_indexed": 19,
      "video_indexed": 0,
      "impressions": 0
    }
  },
  "2025-10-17": {
    "breadcrumbs": {
      "invalid": "N/A",
      "valid": "N/A"
    },
    "coverage": {
      "not_indexed": 8,
      "indexed": 127,
      "impressions": 60
    },
    "https": {
      "non_https_urls": 0,
      "https_urls": 26
    },
    "video_indexing": {
      "no_video_indexed": 19,
      "video_indexed": 0,
      "impressions": 0
    }
  },
  "2025-10-18": {
    "breadcrumbs": {
      "invalid": "N/A",
      "valid": "N/A"
    },
    "coverage": {
      "not_indexed": 8,
      "indexed": 127,
      "impressions": 61
    },
    "https": {
      "non_https_urls": 0,
      "https_urls": 23
    },
    "video_indexing": {
      "no_video_indexed": 19,
      "video_indexed": 0,
      "impressions": 0
    }
  },
  "2025-10-19": {
    "breadcrumbs": {
      "invalid": "N/A",
      "valid": "N/A"
    },
    "coverage": {
      "not_indexed": 9,
      "indexed": 126,
      "impressions": 54
    },
    "https": {
      "non_https_urls": 0,
      "https_urls": 15
    },
    "video_indexing": {
      "no_video_indexed": 19,
      "video_indexed": 0,
      "impressions": 0
    }
  },
  "2025-10-20": {
    "breadcrumbs": {
      "invalid": "N/A",
      "valid": "N/A"
    },
    "coverage": {
      "not_indexed": 9,
      "indexed": 126,
      "impressions": 51
    },
    "https": {
      "non_https_urls": 0,
      "https_urls": 5
    },
    "video_indexing": {
      "no_video_indexed": 19,
      "video_indexed": 0,
      "impressions": 0
    }
  },
  "2025-10-21": {
    "breadcrumbs": {
      "invalid": "N/A",
      "valid": "N/A"
    },
    "coverage": {
      "not_indexed": 9,
      "indexed": 126,
      "impressions": 36
    },
    "https": {
      "non_https_urls": 0,
      "https_urls": 5
    },
    "video_indexing": {
      "no_video_indexed": 17,
      "video_indexed": 0,
      "impressions": 0
    }
  },
  "2025-10-22": {
    "breadcrumbs": {
      "invalid": "N/A",
      "valid": "N/A"
    },
    "coverage": {
      "not_indexed": 14,
      "indexed": 121,
      "impressions": 55
    },
    "https": {
      "non_https_urls": 0,
      "https_urls": 5
    },
    "video_indexing": {
      "no_video_indexed": 17,
      "video_indexed": 0,
      "impressions": 0
    }
  },
  "2025-10-23": {
    "breadcrumbs": {
      "invalid": "N/A",
      "valid": "N/A"
    },
    "coverage": {
      "not_indexed": 14,
      "indexed": 121,
      "impressions": 41
    },
    "https": {
      "non_https_urls": 0,
      "https_urls": 4
    },
    "video_indexing": {
      "no_video_indexed": 17,
      "video_indexed": 0,
      "impressions": 0
    }
  },
  "2025-10-24": {
    "breadcrumbs": {
      "invalid": "N/A",
      "valid": "N/A"
    },
    "coverage": {
      "not_indexed": 14,
      "indexed": 121,
      "impressions": 56
    },
    "https": {
      "non_https_urls": 0,
      "https_urls": 3
    },
    "video_indexing": {
      "no_video_indexed": 14,
      "video_indexed": 0,
      "impressions": 0
    }
  },
  "2025-10-25": {
    "breadcrumbs": {
      "invalid": "N/A",
      "valid": "N/A"
    },
    "coverage": {
      "not_indexed": 14,
      "indexed": 121,
      "impressions": 15
    },
    "https": {
      "non_https_urls": 0,
      "https_urls": 2
    },
    "video_indexing": {
      "no_video_indexed": 14,
      "video_indexed": 0,
      "impressions": 0
    }
  },
  "2025-10-26": {
    "breadcrumbs": {
      "invalid": "N/A",
      "valid": "N/A"
    },
    "coverage": {
      "not_indexed": 20,
      "indexed": 115,
      "impressions": 21
    },
    "https": {
      "non_https_urls": 0,
      "https_urls": 0
    },
    "video_indexing": {
      "no_video_indexed": 14,
      "video_indexed": 0,
      "impressions": 0
    }
  },
  "2025-10-27": {
    "breadcrumbs": {
      "invalid": "N/A",
      "valid": "N/A"
    },
    "coverage": {
      "not_indexed": 20,
      "indexed": 115,
      "impressions": 24
    },
    "https": {
      "non_https_urls": 0,
      "https_urls": 0
    },
    "video_indexing": {
      "no_video_indexed": 14,
      "video_indexed": 0,
      "impressions": 0
    }
  },
  "2025-10-28": {
    "breadcrumbs": {
      "invalid": "N/A",
      "valid": "N/A"
    },
    "coverage": {
      "not_indexed": 20,
      "indexed": 115,
      "impressions": 23
    },
    "https": {
      "non_https_urls": 0,
      "https_urls": 0
    },
    "video_indexing": {
      "no_video_indexed": 14,
      "video_indexed": 0,
      "impressions": 0
    }
  },
  "2025-10-29": {
    "breadcrumbs": {
      "invalid": "N/A",
      "valid": "N/A"
    },
    "coverage": {
      "not_indexed": 21,
      "indexed": 114,
      "impressions": 28
    },
    "https": {
      "non_https_urls": 0,
      "https_urls": 0
    },
    "video_indexing": {
      "no_video_indexed": 14,
      "video_indexed": 0,
      "impressions": 0
    }
  },
  "2025-10-30": {
    "breadcrumbs": {
      "invalid": "N/A",
      "valid": "N/A"
    },
    "coverage": {
      "not_indexed": 21,
      "indexed": 114,
      "impressions": 25
    },
    "https": {
      "non_https_urls": 0,
      "https_urls": 0
    },
    "video_indexing": {
      "no_video_indexed": 14,
      "video_indexed": 0,
      "impressions": 0
    }
  },
  "2025-10-31": {
    "breadcrumbs": {
      "invalid": "N/A",
      "valid": "N/A"
    },
    "coverage": {
      "not_indexed": 21,
      "indexed": 114,
      "impressions": 30
    },
    "https": {
      "non_https_urls": 0,
      "https_urls": 0
    },
    "video_indexing": {
      "no_video_indexed": 13,
      "video_indexed": 0,
      "impressions": 0
    }
  },
  "2025-11-01": {
    "breadcrumbs": {
      "invalid": "N/A",
      "valid": "N/A"
    },
    "coverage": {
      "not_indexed": 21,
      "indexed": 114,
      "impressions": 23
    },
    "https": {
      "non_https_urls": 0,
      "https_urls": 0
    },
    "video_indexing": {
      "no_video_indexed": 13,
      "video_indexed": 0,
      "impressions": 0
    }
  },
  "2025-11-02": {
    "breadcrumbs": {
      "invalid": "N/A",
      "valid": "N/A"
    },
    "coverage": {
      "not_indexed": 28,
      "indexed": 107,
      "impressions": 25
    },
    "https": {
      "non_https_urls": 0,
      "https_urls": 0
    },
    "video_indexing": {
      "no_video_indexed": 13,
      "video_indexed": 0,
      "impressions": 0
    }
  },
  "2025-11-03": {
    "breadcrumbs": {
      "invalid": "N/A",
      "valid": "N/A"
    },
    "coverage": {
      "not_indexed": 28,
      "indexed": 107,
      "impressions": 27
    },
    "https": {
      "non_https_urls": 0,
      "https_urls": 0
    },
    "video_indexing": {
      "no_video_indexed": 13,
      "video_indexed": 0,
      "impressions": 0
    }
  },
  "2025-11-04": {
    "breadcrumbs": {
      "invalid": "N/A",
      "valid": "N/A"
    },
    "coverage": {
      "not_indexed": 28,
      "indexed": 107,
      "impressions": 28
    },
    "https": {
      "non_https_urls": 0,
      "https_urls": 0
    },
    "video_indexing": {
      "no_video_indexed": 11,
      "video_indexed": 0,
      "impressions": 0
    }
  },
  "2025-11-05": {
    "breadcrumbs": {
      "invalid": "N/A",
      "valid": "N/A"
    },
    "coverage": {
      "not_indexed": 36,
      "indexed": 99,
      "impressions": 13
    },
    "https": {
      "non_https_urls": 0,
      "https_urls": 0
    },
    "video_indexing": {
      "no_video_indexed": 11,
      "video_indexed": 0,
      "impressions": 0
    }
  },
  "2025-11-06": {
    "breadcrumbs": {
      "invalid": "N/A",
      "valid": "N/A"
    },
    "coverage": {
      "not_indexed": 36,
      "indexed": 99,
      "impressions": 19
    },
    "https": {
      "non_https_urls": 0,
      "https_urls": 0
    },
    "video_indexing": {
      "no_video_indexed": 11,
      "video_indexed": 0,
      "impressions": 0
    }
  },
  "2025-11-07": {
    "breadcrumbs": {
      "invalid": "N/A",
      "valid": "N/A"
    },
    "coverage": {
      "not_indexed": 36,
      "indexed": 99,
      "impressions": 9
    },
    "https": {
      "non_https_urls": 0,
      "https_urls": 0
    },
    "video_indexing": {
      "no_video_indexed": 9,
      "video_indexed": 0,
      "impressions": 0
    }
  },
  "2025-11-08": {
    "breadcrumbs": {
      "invalid": "N/A",
      "valid": "N/A"
    },
    "coverage": {
      "not_indexed": 36,
      "indexed": 99,
      "impressions": 10
    },
    "https": {
      "non_https_urls": 0,
      "https_urls": 0
    },
    "video_indexing": {
      "no_video_indexed": 9,
      "video_indexed": 0,
      "impressions": 0
    }
  },
  "2025-11-09": {
    "breadcrumbs": {
      "invalid": "N/A",
      "valid": "N/A"
    },
    "coverage": {
      "not_indexed": 36,
      "indexed": 99,
      "impressions": 15
    },
    "https": {
      "non_https_urls": 0,
      "https_urls": 0
    },
    "video_indexing": {
      "no_video_indexed": 9,
      "video_indexed": 0,
      "impressions": 0
    }
  },
  "2025-11-10": {
    "breadcrumbs": {
      "invalid": "N/A",
      "valid": "N/A"
    },
    "coverage": {
      "not_indexed": 36,
      "indexed": 99,
      "impressions": 13
    },
    "https": {
      "non_https_urls": 0,
      "https_urls": 0
    },
    "video_indexing": {
      "no_video_indexed": 9,
      "video_indexed": 0,
      "impressions": 0
    }
  },
  "2025-11-11": {
    "breadcrumbs": {
      "invalid": "N/A",
      "valid": "N/A"
    },
    "coverage": {
      "not_indexed": 36,
      "indexed": 99,
      "impressions": 9
    },
    "https": {
      "non_https_urls": 0,
      "https_urls": 0
    },
    "video_indexing": {
      "no_video_indexed": 9,
      "video_indexed": 0,
      "impressions": 0
    }
  },
  "2025-11-12": {
    "breadcrumbs": {
      "invalid": "N/A",
      "valid": "N/A"
    },
    "coverage": {
      "not_indexed": 38,
      "indexed": 97,
      "impressions": 16
    },
    "https": {
      "non_https_urls": 0,
      "https_urls": 0
    },
    "video_indexing": {
      "no_video_indexed": 9,
      "video_indexed": 0,
      "impressions": 0
    }
  },
  "2025-11-13": {
    "breadcrumbs": {
      "invalid": "N/A",
      "valid": "N/A"
    },
    "coverage": {
      "not_indexed": 38,
      "indexed": 97,
      "impressions": 11
    },
    "https": {
      "non_https_urls": 0,
      "https_urls": 0
    },
    "video_indexing": {
      "no_video_indexed": 9,
      "video_indexed": 0,
      "impressions": 0
    }
  },
  "2025-11-14": {
    "breadcrumbs": {
      "invalid": "N/A",
      "valid": "N/A"
    },
    "coverage": {
      "not_indexed": 38,
      "indexed": 97,
      "impressions": 10
    },
    "https": {
      "non_https_urls": 0,
      "https_urls": 0
    },
    "video_indexing": {
      "no_video_indexed": 8,
      "video_indexed": 0,
      "impressions": 0
    }
  },
  "2025-11-15": {
    "breadcrumbs": {
      "invalid": "N/A",
      "valid": "N/A"
    },
    "coverage": {
      "not_indexed": 38,
      "indexed": 97,
      "impressions": 8
    },
    "https": {
      "non_https_urls": 0,
      "https_urls": 0
    },
    "video_indexing": {
      "no_video_indexed": 8,
      "video_indexed": 0,
      "impressions": 0
    }
  },
  "2025-11-16": {
    "breadcrumbs": {
      "invalid": "N/A",
      "valid": "N/A"
    },
    "coverage": {
      "not_indexed": 43,
      "indexed": 92,
      "impressions": 18
    },
    "https": {
      "non_https_urls": 0,
      "https_urls": 0
    },
    "video_indexing": {
      "no_video_indexed": 8,
      "video_indexed": 0,
      "impressions": 0
    }
  },
  "2025-11-17": {
    "breadcrumbs": {
      "invalid": "N/A",
      "valid": "N/A"
    },
    "coverage": {
      "not_indexed": 43,
      "indexed": 92,
      "impressions": 16
    },
    "https": {
      "non_https_urls": 0,
      "https_urls": 0
    },
    "video_indexing": {
      "no_video_indexed": 8,
      "video_indexed": 0,
      "impressions": 0
    }
  },
  "2025-11-18": {
    "breadcrumbs": {
      "invalid": "N/A",
      "valid": "N/A"
    },
    "coverage": {
      "not_indexed": 43,
      "indexed": 92,
      "impressions": 20
    },
    "https": {
      "non_https_urls": 0,
      "https_urls": 0
    },
    "video_indexing": {
      "no_video_indexed": 8,
      "video_indexed": 0,
      "impressions": 0
    }
  },
  "2025-11-19": {
    "breadcrumbs": {
      "invalid": "N/A",
      "valid": "N/A"
    },
    "coverage": {
      "not_indexed": 46,
      "indexed": 89,
      "impressions": 11
    },
    "https": {
      "non_https_urls": 0,
      "https_urls": 0
    },
    "video_indexing": {
      "no_video_indexed": 8,
      "video_indexed": 0,
      "impressions": 0
    }
  },
  "2025-11-20": {
    "breadcrumbs": {
      "invalid": "N/A",
      "valid": "N/A"
    },
    "coverage": {
      "not_indexed": 46,
      "indexed": 89,
      "impressions": 15
    },
    "https": {
      "non_https_urls": 0,
      "https_urls": 0
    },
    "video_indexing": {
      "no_video_indexed": 8,
      "video_indexed": 0,
      "impressions": 0
    }
  },
  "2025-11-21": {
    "breadcrumbs": {
      "invalid": "N/A",
      "valid": "N/A"
    },
    "coverage": {
      "not_indexed": 46,
      "indexed": 89,
      "impressions": 14
    },
    "https": {
      "non_https_urls": 0,
      "https_urls": 0
    },
    "video_indexing": {
      "no_video_indexed": 6,
      "video_indexed": 0,
      "impressions": 0
    }
  },
  "2025-11-22": {
    "breadcrumbs": {
      "invalid": "N/A",
      "valid": "N/A"
    },
    "coverage": {
      "not_indexed": 46,
      "indexed": 89,
      "impressions": 14
    },
    "https": {
      "non_https_urls": 0,
      "https_urls": 0
    },
    "video_indexing": {
      "no_video_indexed": 6,
      "video_indexed": 0,
      "impressions": 0
    }
  },
  "2025-11-23": {
    "breadcrumbs": {
      "invalid": "N/A",
      "valid": "N/A"
    },
    "coverage": {
      "not_indexed": "N/A",
      "indexed": "N/A",
      "impressions": "N/A"
    },
    "https": {
      "non_https_urls": 0,
      "https_urls": 0
    },
    "video_indexing": {
      "no_video_indexed": 6,
      "video_indexed": 0,
      "impressions": 0
    }
  },
  "2025-11-24": {
    "breadcrumbs": {
      "invalid": "N/A",
      "valid": "N/A"
    },
    "coverage": {
      "not_indexed": "N/A",
      "indexed": "N/A",
      "impressions": "N/A"
    },
    "https": {
      "non_https_urls": 0,
      "https_urls": 0
    },
    "video_indexing": {
      "no_video_indexed": 6,
      "video_indexed": 0,
      "impressions": 0
    }
  },
  "2025-11-25": {
    "breadcrumbs": {
      "invalid": "N/A",
      "valid": "N/A"
    },
    "coverage": {
      "not_indexed": "N/A",
      "indexed": "N/A",
      "impressions": "N/A"
    },
    "https": {
      "non_https_urls": 0,
      "https_urls": 0
    },
    "video_indexing": {
      "no_video_indexed": 6,
      "video_indexed": 0,
      "impressions": 0
    }
  },
  "2025-11-26": {
    "breadcrumbs": {
      "invalid": "N/A",
      "valid": "N/A"
    },
    "coverage": {
      "not_indexed": "N/A",
      "indexed": "N/A",
      "impressions": "N/A"
    },
    "https": {
      "non_https_urls": 0,
      "https_urls": 0
    },
    "video_indexing": {
      "no_video_indexed": 6,
      "video_indexed": 0,
      "impressions": 0
    }
  },
  "2025-11-27": {
    "breadcrumbs": {
      "invalid": "N/A",
      "valid": "N/A"
    },
    "coverage": {
      "not_indexed": "N/A",
      "indexed": "N/A",
      "impressions": "N/A"
    },
    "https": {
      "non_https_urls": 0,
      "https_urls": 0
    },
    "video_indexing": {
      "no_video_indexed": 6,
      "video_indexed": 0,
      "impressions": 0
    }
  },
  "2025-11-28": {
    "breadcrumbs": {
      "invalid": "N/A",
      "valid": "N/A"
    },
    "coverage": {
      "not_indexed": "N/A",
      "indexed": "N/A",
      "impressions": "N/A"
    },
    "https": {
      "non_https_urls": 0,
      "https_urls": 0
    },
    "video_indexing": {
      "no_video_indexed": 6,
      "video_indexed": 0,
      "impressions": 0
    }
  },
  "2025-11-29": {
    "breadcrumbs": {
      "invalid": "N/A",
      "valid": "N/A"
    },
    "coverage": {
      "not_indexed": "N/A",
      "indexed": "N/A",
      "impressions": "N/A"
    },
    "https": {
      "non_https_urls": 0,
      "https_urls": 0
    },
    "video_indexing": {
      "no_video_indexed": 6,
      "video_indexed": 0,
      "impressions": 0
    }
  },
  "2025-11-30": {
    "breadcrumbs": {
      "invalid": "N/A",
      "valid": "N/A"
    },
    "coverage": {
      "not_indexed": "N/A",
      "indexed": "N/A",
      "impressions": "N/A"
    },
    "https": {
      "non_https_urls": 0,
      "https_urls": 0
    },
    "video_indexing": {
      "no_video_indexed": 6,
      "video_indexed": 0,
      "impressions": 0
    }
  },
  "2025-12-01": {
    "breadcrumbs": {
      "invalid": "N/A",
      "valid": "N/A"
    },
    "coverage": {
      "not_indexed": "N/A",
      "indexed": "N/A",
      "impressions": "N/A"
    },
    "https": {
      "non_https_urls": 0,
      "https_urls": 0
    },
    "video_indexing": {
      "no_video_indexed": 6,
      "video_indexed": 0,
      "impressions": 0
    }
  },
  "2025-12-02": {
    "breadcrumbs": {
      "invalid": "N/A",
      "valid": "N/A"
    },
    "coverage": {
      "not_indexed": "N/A",
      "indexed": "N/A",
      "impressions": "N/A"
    },
    "https": {
      "non_https_urls": 0,
      "https_urls": 0
    },
    "video_indexing": {
      "no_video_indexed": 6,
      "video_indexed": 0,
      "impressions": 0
    }
  },
  "2025-12-03": {
    "breadcrumbs": {
      "invalid": "N/A",
      "valid": "N/A"
    },
    "coverage": {
      "not_indexed": "N/A",
      "indexed": "N/A",
      "impressions": "N/A"
    },
    "https": {
      "non_https_urls": 0,
      "https_urls": 0
    },
    "video_indexing": {
      "no_video_indexed": 6,
      "video_indexed": 0,
      "impressions": 0
    }
  },
  "2025-12-04": {
    "breadcrumbs": {
      "invalid": "N/A",
      "valid": "N/A"
    },
    "coverage": {
      "not_indexed": "N/A",
      "indexed": "N/A",
      "impressions": "N/A"
    },
    "https": {
      "non_https_urls": 0,
      "https_urls": 0
    },
    "video_indexing": {
      "no_video_indexed": 6,
      "video_indexed": 0,
      "impressions": 0
    }
  },
  "2025-12-05": {
    "breadcrumbs": {
      "invalid": "N/A",
      "valid": "N/A"
    },
    "coverage": {
      "not_indexed": "N/A",
      "indexed": "N/A",
      "impressions": "N/A"
    },
    "https": {
      "non_https_urls": 0,
      "https_urls": 0
    },
    "video_indexing": {
      "no_video_indexed": 4,
      "video_indexed": 0,
      "impressions": 0
    }
  },
  "2025-12-06": {
    "breadcrumbs": {
      "invalid": "N/A",
      "valid": "N/A"
    },
    "coverage": {
      "not_indexed": "N/A",
      "indexed": "N/A",
      "impressions": "N/A"
    },
    "https": {
      "non_https_urls": 0,
      "https_urls": 0
    },
    "video_indexing": {
      "no_video_indexed": 4,
      "video_indexed": 0,
      "impressions": 0
    }
  },
  "2025-12-07": {
    "breadcrumbs": {
      "invalid": "N/A",
      "valid": "N/A"
    },
    "coverage": {
      "not_indexed": "N/A",
      "indexed": "N/A",
      "impressions": "N/A"
    },
    "https": {
      "non_https_urls": 0,
      "https_urls": 0
    },
    "video_indexing": {
      "no_video_indexed": 4,
      "video_indexed": 0,
      "impressions": 0
    }
  },
  "2025-12-08": {
    "breadcrumbs": {
      "invalid": "N/A",
      "valid": "N/A"
    },
    "coverage": {
      "not_indexed": "N/A",
      "indexed": "N/A",
      "impressions": "N/A"
    },
    "https": {
      "non_https_urls": 0,
      "https_urls": 0
    },
    "video_indexing": {
      "no_video_indexed": 4,
      "video_indexed": 0,
      "impressions": 0
    }
  },
  "2025-12-09": {
    "breadcrumbs": {
      "invalid": "N/A",
      "valid": "N/A"
    },
    "coverage": {
      "not_indexed": "N/A",
      "indexed": "N/A",
      "impressions": "N/A"
    },
    "https": {
      "non_https_urls": 0,
      "https_urls": 0
    },
    "video_indexing": {
      "no_video_indexed": 4,
      "video_indexed": 0,
      "impressions": 0
    }
  },
  "2025-12-10": {
    "breadcrumbs": {
      "invalid": "N/A",
      "valid": "N/A"
    },
    "coverage": {
      "not_indexed": "N/A",
      "indexed": "N/A",
      "impressions": "N/A"
    },
    "https": {
      "non_https_urls": 0,
      "https_urls": 0
    },
    "video_indexing": {
      "no_video_indexed": 4,
      "video_indexed": 0,
      "impressions": 0
    }
  },
  "2025-12-11": {
    "breadcrumbs": {
      "invalid": "N/A",
      "valid": "N/A"
    },
    "coverage": {
      "not_indexed": "N/A",
      "indexed": "N/A",
      "impressions": "N/A"
    },
    "https": {
      "non_https_urls": 0,
      "https_urls": 0
    },
    "video_indexing": {
      "no_video_indexed": 4,
      "video_indexed": 0,
      "impressions": 0
    }
  },
  "2025-12-12": {
    "breadcrumbs": {
      "invalid": "N/A",
      "valid": "N/A"
    },
    "coverage": {
      "not_indexed": "N/A",
      "indexed": "N/A",
      "impressions": "N/A"
    },
    "https": {
      "non_https_urls": 0,
      "https_urls": 0
    },
    "video_indexing": {
      "no_video_indexed": "N/A",
      "video_indexed": "N/A",
      "impressions": "N/A"
    }
  }
}